r00pykit/__init__.py
r00pykit/text.py
r00pykit/time_it.py
r00pykit-0.1.4.dist-info/METADATA
r00pykit-0.1.4.dist-info/WHEEL
r00pykit-0.1.4.dist-info/RECORD
