Metadata-Version: 2.4
Name: r00pykit
Version: 0.1.4
Requires-Python: >=3.10
Requires-Dist: r00logger
